{
  "sharedDir": "shared",
  "dependenciesDir": "extern",
  "info": {
    "name": "flamingo",
    "id": "flamingo",
    "version": "0.1.0",
    "url": "https://github.com/sc2ad/Flamingo",
    "additionalData": {
      "overrideSoName": "libflamingo.so"
    }
  },
  "dependencies": [
    {
      "id": "capstone",
      "versionRange": "^0.1.0",
      "additionalData": {}
    },
    {
      "id": "paper",
      "versionRange": "^1.0.0",
      "additionalData": {}
    },
    {
      "id": "modloader",
      "versionRange": "^1.0.2",
      "additionalData": {}
    },
    {
      "id": "beatsaber-hook",
      "versionRange": "^3.8.0",
      "additionalData": {}
    },
    {
      "id": "paper",
      "versionRange": "^1.2.9",
      "additionalData": {}
    }
  ],
  "workspace": null
}